horse_with_no_namespace/__about__.py
horse_with_no_namespace/__init__.py
horse_with_no_namespace/pkg_resources.py
~horse_with_no_namespace.pth
horse_with_no_namespace-20251105.1.dist-info/METADATA
horse_with_no_namespace-20251105.1.dist-info/WHEEL
horse_with_no_namespace-20251105.1.dist-info/licenses/LICENSE.txt
horse_with_no_namespace-20251105.1.dist-info/RECORD
