Metadata-Version: 2.4
Name: horse-with-no-namespace
Version: 20251105.1
Project-URL: Documentation, https://github.com/davisagli/horse-with-no-namespace#readme
Project-URL: Issues, https://github.com/davisagli/horse-with-no-namespace/issues
Project-URL: Source, https://github.com/davisagli/horse-with-no-namespace
Author-email: David Glick <david@glicksoftware.com>
License-Expression: MIT
License-File: LICENSE.txt
Classifier: Development Status :: 4 - Beta
Classifier: Programming Language :: Python
Classifier: Programming Language :: Python :: 3.8
Classifier: Programming Language :: Python :: 3.9
Classifier: Programming Language :: Python :: 3.10
Classifier: Programming Language :: Python :: 3.11
Classifier: Programming Language :: Python :: 3.12
Classifier: Programming Language :: Python :: 3.13
Classifier: Programming Language :: Python :: Implementation :: CPython
Classifier: Programming Language :: Python :: Implementation :: PyPy
Requires-Python: >=3.8
